README.md
setup.cfg
setup.py
Chunking.egg-info/PKG-INFO
Chunking.egg-info/SOURCES.txt
Chunking.egg-info/dependency_links.txt
Chunking.egg-info/top_level.txt
chunking/__init__.py
chunking/chunking.py